MANIFEST.in
README.md
setup.py
ssp/__init__.py
ssp/ar.py
ssp/core.py
ssp/gm.py
ssp/test.py
ssp.egg-info/PKG-INFO
ssp.egg-info/SOURCES.txt
ssp.egg-info/dependency_links.txt
ssp.egg-info/entry_points.txt
ssp.egg-info/requires.txt
ssp.egg-info/top_level.txt
ssp/script/__init__.py
ssp/script/codec.py
ssp/script/extracter.py
ssp/script/harmonic.py
ssp/script/linear.py
ssp/script/norms.py
ssp/script/pitch.py
ssp/script/pulse.py
ssp/script/spectrogram.py
ssp/script/warp.py