Metadata-Version: 1.1
Name: ssp
Version: 0.1a7
Summary: SSP
Home-page: http://github.com/bioidiap/ssp
Author: Phil Garner
Author-email: phil.garner@idiap.ch
License: GPLv3
Platform: UNKNOWN
Classifier: Development Status :: 4 - Beta
Classifier: Intended Audience :: Developers
Classifier: License :: OSI Approved :: GNU General Public License v3 (GPLv3)
Classifier: Natural Language :: English
Classifier: Programming Language :: Python
Classifier: Topic :: Scientific/Engineering :: Artificial Intelligence
